[{"title":"colins kahverengi kadın kemer _kadin","priceNew":"169,90","imageUrl":"800/-/Assets/Branch/Originals/145857_0.jpeg","link":"p/kahverengi-kadin-kemer-34010","timestamp":1674209105459,"marka":"colins"},{"title":"colins siyah kadın saç bandı _kadin","priceNew":"29,99","imageUrl":"800/-/Assets/Branch/Originals/147218_0.jpeg","link":"p/siyah-kadin-sac-bandi-33570","timestamp":1673858329152,"marka":"colins"},{"title":"colins bordo kadın saç bandı _kadin","priceNew":"29,99","imageUrl":"800/-/Assets/Branch/Originals/147219_0.jpeg","link":"p/bordo-kadin-sac-bandi-33625","timestamp":1673858329152,"marka":"colins"},{"title":"colins mor kadın saç bandı _kadin","priceNew":"29,99","imageUrl":"800/-/Assets/Branch/Originals/147220_0.jpeg","link":"p/mor-kadin-sac-bandi-33808","timestamp":1673858329152,"marka":"colins"},{"title":"colins mavi kadın saç bandı _kadin","priceNew":"29,99","imageUrl":"800/-/Assets/Branch/Originals/147221_0.jpeg","link":"p/mavi-kadin-sac-bandi-33488","timestamp":1673858329152,"marka":"colins"},{"title":"colins siyah kadın saç bandı _kadin","priceNew":"29,99","imageUrl":"800/-/Assets/Branch/Originals/147222_0.jpeg","link":"p/siyah-kadin-sac-bandi-33537","timestamp":1673858329152,"marka":"colins"},{"title":"colins ekru kadın saç bandı _kadin","priceNew":"29,99","imageUrl":"800/-/Assets/Branch/Originals/147223_0.jpeg","link":"p/ekru-kadin-sac-bandi-33809","timestamp":1673858329152,"marka":"colins"},{"title":"colins pembe kadın saç bandı _kadin","priceNew":"29,99","imageUrl":"800/-/Assets/Branch/Originals/147224_0.jpeg","link":"p/pembe-kadin-sac-bandi-33807","timestamp":1673858329152,"marka":"colins"},{"title":"colins siyah kadın kemer _kadin","priceNew":"169,90","imageUrl":"800/-/Assets/Branch/Originals/151276_0.jpeg","link":"p/siyah-kadin-kemer-34007","timestamp":1674209105459,"marka":"colins"},{"title":"colins baskılı beyaz kadın çorap _kadin","priceNew":"39,95","imageUrl":"800/-/Assets/Branch/Originals/159869_0.jpeg","link":"p/baskili-beyaz-kadin-corap-37507","timestamp":1674209105459,"marka":"colins"},{"title":"colins baskılı siyah kadın çorap _kadin","priceNew":"34,95","imageUrl":"800/-/Assets/Branch/Originals/159870_0.jpeg","link":"p/baskili-siyah-kadin-corap-37508","timestamp":1674209105459,"marka":"colins"},{"title":"colins baskılı mor kadın çorap _kadin","priceNew":"34,95","imageUrl":"800/-/Assets/Branch/Originals/159871_0.jpeg","link":"p/baskili-mor-kadin-corap-37509","timestamp":1674209105459,"marka":"colins"},{"title":"colins baskılı pembe kadın çorap _kadin","priceNew":"34,95","imageUrl":"800/-/Assets/Branch/Originals/159872_0.jpeg","link":"p/baskili-pembe-kadin-corap-37510","timestamp":1674209105459,"marka":"colins"},{"title":"colins baskılı siyah kadın çorap _kadin","priceNew":"34,95","imageUrl":"800/-/Assets/Branch/Originals/159873_0.jpeg","link":"p/baskili-siyah-kadin-corap-37511","timestamp":1674209105459,"marka":"colins"},{"title":"colins bej kadın kemer _kadin","priceNew":"49,95","imageUrl":"800/-/Assets/Branch/Originals/159896_0.jpeg","link":"p/bej-kadin-kemer-37386","timestamp":1674209105459,"marka":"colins"},{"title":"colins boyunluk yeşil kadın atkı _kadin","priceNew":"169,95","imageUrl":"800/-/Assets/Branch/Originals/160442_0.jpeg","link":"p/boyunluk-yesil-kadin-atki-37794","timestamp":1674209105459,"marka":"colins"},{"title":"colins bej kadın saç bandı _kadin","priceNew":"59,95","imageUrl":"800/-/Assets/Branch/Originals/160445_0.jpeg","link":"p/bej-kadin-sac-bandi-37830","timestamp":1673858329152,"marka":"colins"},{"title":"colins siyah kadın saç bandı _kadin","priceNew":"59,95","imageUrl":"800/-/Assets/Branch/Originals/160446_0.jpeg","link":"p/siyah-kadin-sac-bandi-37764","timestamp":1673858329152,"marka":"colins"},{"title":"colins gri kadın saç bandı _kadin","priceNew":"59,95","imageUrl":"800/-/Assets/Branch/Originals/160447_0.jpeg","link":"p/gri-kadin-sac-bandi-37720","timestamp":1673858329152,"marka":"colins"},{"title":"colins baskılı gri kadın çorap _kadin","priceNew":"34,95","imageUrl":"800/-/Assets/Branch/Originals/160634_0.jpeg","link":"p/baskili-gri-kadin-corap-37665","timestamp":1674209105459,"marka":"colins"},{"title":"colins baskılı siyah kadın çorap _kadin","priceNew":"34,95","imageUrl":"800/-/Assets/Branch/Originals/160635_0.jpeg","link":"p/baskili-siyah-kadin-corap-37666","timestamp":1674209105459,"marka":"colins"},{"title":"colins baskılı pembe kadın çorap _kadin","priceNew":"34,95","imageUrl":"800/-/Assets/Branch/Originals/160636_0.jpeg","link":"p/baskili-pembe-kadin-corap-37667","timestamp":1674209105459,"marka":"colins"},{"title":"colins baskılı bej kadın çorap _kadin","priceNew":"34,95","imageUrl":"800/-/Assets/Branch/Originals/160637_0.jpeg","link":"p/baskili-bej-kadin-corap-37668","timestamp":1674209105459,"marka":"colins"},{"title":"colins baskılı bej kadın çorap _kadin","priceNew":"34,95","imageUrl":"800/-/Assets/Branch/Originals/160638_0.jpeg","link":"p/baskili-bej-kadin-corap-37673","timestamp":1674209105459,"marka":"colins"},{"title":"colins baskılı gri kadın çorap _kadin","priceNew":"34,95","imageUrl":"800/-/Assets/Branch/Originals/160639_0.jpeg","link":"p/baskili-gri-kadin-corap-37674","timestamp":1674209105459,"marka":"colins"},{"title":"colins baskılı siyah kadın çorap _kadin","priceNew":"34,95","imageUrl":"800/-/Assets/Branch/Originals/160642_0.jpeg","link":"p/baskili-siyah-kadin-corap-37679","timestamp":1674209105459,"marka":"colins"},{"title":"colins baskılı pembe kadın çorap _kadin","priceNew":"34,95","imageUrl":"800/-/Assets/Branch/Originals/160643_0.jpeg","link":"p/baskili-pembe-kadin-corap-37680","timestamp":1674209105459,"marka":"colins"},{"title":"colins baskılı yeşil kadın bere _kadin","priceNew":"59,95","imageUrl":"800/-/Assets/Branch/Originals/160673_0.jpeg","link":"p/baskili-yesil-kadin-bere-37807","timestamp":1674209105459,"marka":"colins"},{"title":"colins baskılı siyah kadın çorap _kadin","priceNew":"34,95","imageUrl":"800/-/Assets/Branch/Originals/162421_0.jpeg","link":"p/baskili-siyah-kadin-corap-37541","timestamp":1674209105459,"marka":"colins"},{"title":"colins çiçek baskılı siyah kadın çorap _kadin","priceNew":"44,90","imageUrl":"800/-/Assets/Branch/Originals/162444_0.jpeg","link":"p/cicek-baskili-siyah-kadin-corap-37681","timestamp":1673858329152,"marka":"colins"},{"title":"colins mavi kadın çorap _kadin","priceNew":"44,95","imageUrl":"800/-/Assets/Branch/Originals/162445_0.jpeg","link":"p/mavi-kadin-corap-37694","timestamp":1674130929256,"marka":"colins"},{"title":"colins sarı kadın çorap _kadin","priceNew":"39,95","imageUrl":"800/-/Assets/Branch/Originals/162446_0.jpeg","link":"p/sari-kadin-corap-37695","timestamp":1674130929256,"marka":"colins"},{"title":"colins bej kadın eldiven _kadin","priceNew":"69,95","imageUrl":"800/-/Assets/Branch/Originals/162469_0.jpeg","link":"p/bej-kadin-eldiven-37570","timestamp":1674209105459,"marka":"colins"},{"title":"colins siyah kadın kemer _kadin","priceNew":"119,90","imageUrl":"800/-/Assets/Branch/Originals/162471_0.jpeg","link":"p/siyah-kadin-kemer-37537","timestamp":1674209105459,"marka":"colins"},{"title":"colins baskılı mavi kadın çorap _kadin","priceNew":"59,90","imageUrl":"800/-/Assets/Branch/Originals/163942_0.jpeg","link":"p/baskili-mavi-kadin-corap-38952","timestamp":1674205440411,"marka":"colins"},{"title":"colins siyah kadın kemer _kadin","priceNew":"134,90","imageUrl":"800/-/Assets/Branch/Originals/164038_0.jpeg","link":"p/siyah-kadin-kemer-38913","timestamp":1674130929256,"marka":"colins"},{"title":"colins bej kadın kemer _kadin","priceNew":"134,90","imageUrl":"800/-/Assets/Branch/Originals/164039_0.jpeg","link":"p/bej-kadin-kemer-38914","timestamp":1673858329152,"marka":"colins"},{"title":"colins siyah kadın kemer _kadin","priceNew":"134,90","imageUrl":"800/-/Assets/Branch/Originals/164040_0.jpeg","link":"p/siyah-kadin-kemer-38915","timestamp":1674130929256,"marka":"colins"},{"title":"colins siyah kadın kemer _kadin","priceNew":"134,90","imageUrl":"800/-/Assets/Branch/Originals/164041_0.jpeg","link":"p/siyah-kadin-kemer-38916","timestamp":1674130929256,"marka":"colins"},{"title":"colins siyah kadın kemer _kadin","priceNew":"134,90","imageUrl":"800/-/Assets/Branch/Originals/164042_0.jpeg","link":"p/siyah-kadin-kemer-38917","timestamp":1674209105459,"marka":"colins"},{"title":"colins siyah kadın kemer _kadin","priceNew":"134,90","imageUrl":"800/-/Assets/Branch/Originals/164043_0.jpeg","link":"p/siyah-kadin-kemer-38922","timestamp":1674130929257,"marka":"colins"},{"title":"colins siyah kadın kemer _kadin","priceNew":"134,90","imageUrl":"800/-/Assets/Branch/Originals/164044_0.jpeg","link":"p/siyah-kadin-kemer-38923","timestamp":1674130929257,"marka":"colins"},{"title":"colins siyah kadın kemer _kadin","priceNew":"134,90","imageUrl":"800/-/Assets/Branch/Originals/164045_0.jpeg","link":"p/siyah-kadin-kemer-38924","timestamp":1674209105459,"marka":"colins"},{"title":"colins siyah kadın kemer _kadin","priceNew":"134,90","imageUrl":"800/-/Assets/Branch/Originals/164046_0.jpeg","link":"p/siyah-kadin-kemer-38925","timestamp":1674209105459,"marka":"colins"},{"title":"colins siyah kadın kemer _kadin","priceNew":"134,90","imageUrl":"800/-/Assets/Branch/Originals/164049_0.jpeg","link":"p/siyah-kadin-kemer-38927","timestamp":1674209105459,"marka":"colins"},{"title":"colins babet çok renkli kadın çorap _kadin","priceNew":"74,90","imageUrl":"800/-/Assets/Branch/Originals/164050_0.jpeg","link":"p/babet-cok-renkli-kadin-corap-38928","timestamp":1674205440411,"marka":"colins"},{"title":"colins siyah kadın çorap _kadin","priceNew":"59,90","imageUrl":"800/-/Assets/Branch/Originals/164051_0.jpeg","link":"p/siyah-kadin-corap-38929","timestamp":1674130929256,"marka":"colins"},{"title":"colins baskılı antrasit kadın çorap _kadin","priceNew":"49,90","imageUrl":"800/-/Assets/Branch/Originals/164053_0.jpeg","link":"p/baskili-antrasit-kadin-corap-38934","timestamp":1674205440411,"marka":"colins"},{"title":"colins babet siyah kadın çorap _kadin","priceNew":"39,90","imageUrl":"800/-/Assets/Branch/Originals/164054_0.jpeg","link":"p/babet-siyah-kadin-corap-38935","timestamp":1674205440411,"marka":"colins"},{"title":"colins babet ekru kadın çorap _kadin","priceNew":"39,90","imageUrl":"800/-/Assets/Branch/Originals/164055_0.jpeg","link":"p/babet-ekru-kadin-corap-38936","timestamp":1674205440411,"marka":"colins"},{"title":"colins siyah kadın çorap _kadin","priceNew":"59,90","imageUrl":"800/-/Assets/Branch/Originals/164057_0.jpeg","link":"p/siyah-kadin-corap-38938","timestamp":1674130929256,"marka":"colins"},{"title":"colins beyaz kadın çorap _kadin","priceNew":"59,90","imageUrl":"800/-/Assets/Branch/Originals/164058_0.jpeg","link":"p/beyaz-kadin-corap-38939","timestamp":1673858329152,"marka":"colins"},{"title":"colins babet gri kadın çorap _kadin","priceNew":"74,90","imageUrl":"800/-/Assets/Branch/Originals/164059_0.jpeg","link":"p/babet-gri-kadin-corap-38940","timestamp":1674205440411,"marka":"colins"},{"title":"colins baskılı gri kadın çorap _kadin","priceNew":"49,90","imageUrl":"800/-/Assets/Branch/Originals/164060_0.jpeg","link":"p/baskili-gri-kadin-corap-38944","timestamp":1674205440411,"marka":"colins"},{"title":"colins baskılı ekru kadın çorap _kadin","priceNew":"49,90","imageUrl":"800/-/Assets/Branch/Originals/164061_0.jpeg","link":"p/baskili-ekru-kadin-corap-38945","timestamp":1674205440411,"marka":"colins"},{"title":"colins baskılı gri kadın çorap _kadin","priceNew":"49,90","imageUrl":"800/-/Assets/Branch/Originals/164062_0.jpeg","link":"p/baskili-gri-kadin-corap-38947","timestamp":1674205440411,"marka":"colins"},{"title":"colins mavi kadın çorap _kadin","priceNew":"59,90","imageUrl":"800/-/Assets/Branch/Originals/164064_0.jpeg","link":"p/mavi-kadin-corap-38950","timestamp":1674130929256,"marka":"colins"},{"title":"colins ekru kadın çorap _kadin","priceNew":"59,90","imageUrl":"800/-/Assets/Branch/Originals/164065_0.jpeg","link":"p/ekru-kadin-corap-38951","timestamp":1674130929256,"marka":"colins"},{"title":"colins siyah kadın kemer _kadin","priceNew":"199,90","imageUrl":"800/-/Assets/Branch/Originals/165618_0.jpeg","link":"p/siyah-kadin-kemer-38918","timestamp":1674130929256,"marka":"colins"},{"title":"colins siyah kadın çorap _kadin","priceNew":"39,90","imageUrl":"800/-/Assets/Branch/Originals/165619_0.jpeg","link":"p/siyah-kadin-corap-38953","timestamp":1674130929256,"marka":"colins"},{"title":"colins gri kadın çorap _kadin","priceNew":"39,90","imageUrl":"800/-/Assets/Branch/Originals/165676_0.jpeg","link":"p/gri-kadin-corap-38932","timestamp":1674130929256,"marka":"colins"},{"title":"colins pembe kadın çorap _kadin","priceNew":"39,90","imageUrl":"800/-/Assets/Branch/Originals/165678_0.jpeg","link":"p/pembe-kadin-corap-38941","timestamp":1674130929256,"marka":"colins"},{"title":"colins siyah kadın çorap _kadin","priceNew":"59,90","imageUrl":"800/-/Assets/Branch/Originals/165679_0.jpeg","link":"p/siyah-kadin-corap-38942","timestamp":1674130929256,"marka":"colins"},{"title":"colins beyaz kadın çorap _kadin","priceNew":"59,90","imageUrl":"800/-/Assets/Branch/Originals/165680_0.jpeg","link":"p/beyaz-kadin-corap-38943","timestamp":1674014533065,"marka":"colins"},{"title":"colins beyaz kadın çorap _kadin","priceNew":"59,90","imageUrl":"800/-/Assets/Branch/Originals/165681_0.jpeg","link":"p/beyaz-kadin-corap-38946","timestamp":1674014533065,"marka":"colins"},{"title":"colins siyah kadın kemer _kadin","priceNew":"199,90","imageUrl":"800/-/Assets/Branch/Originals/165699_0.jpeg","link":"p/siyah-kadin-kemer-38920","timestamp":1674130929257,"marka":"colins"}]