[{"groupName":"BOYU","keywords":[{"keyword":"midi","index":"5-","count":9}]},{"groupName":"DESENLI","keywords":[{"keyword":"çiçek desen","index":"8-","count":1},{"keyword":"çiçekli","index":"9-","count":1}]},{"groupName":"MODEL","keywords":[{"keyword":"kokteyl","index":"113-","count":1},{"keyword":"triko","index":"134-","count":1}]},{"groupName":"RENK","keywords":[{"keyword":"açık","index":"143-","count":9},{"keyword":"haki","index":"149-","count":1},{"keyword":"kırmızı","index":"151-","count":1},{"keyword":"lila","index":"154-","count":1},{"keyword":"mavi","index":"161-","count":1},{"keyword":"pembe","index":"163-","count":1},{"keyword":"siyah","index":"157-","count":2},{"keyword":"yeşil","index":"158-","count":1}]},{"groupName":"YAKASI","keywords":[{"keyword":"dik yaka","index":"177-","count":1},{"keyword":"v yaka","index":"182-","count":1}]}]