[{"groupName":"BOYU","keywords":[{"keyword":"midi","index":"5-","count":1}]},{"groupName":"DESENLI","keywords":[{"keyword":"çiçekli","index":"9-","count":17}]},{"groupName":"KOLU","keywords":[{"keyword":"uzun kollu","index":"32-","count":17}]},{"groupName":"KUMAŞ","keywords":[{"keyword":"şifon","index":"57-","count":17}]},{"groupName":"RENK","keywords":[{"keyword":"kırmızı","index":"151-","count":1}]},{"groupName":"YAKASI","keywords":[{"keyword":"bisiklet yaka","index":"174-","count":8},{"keyword":"dik yaka","index":"177-","count":1},{"keyword":"kruvaze yaka","index":"171-","count":2},{"keyword":"v yaka","index":"182-","count":3}]}]