{"101-":{"count":3,"keywordTitle":"baqa","imageUrl":{"src":"/Uploads/UrunResimleri/thumb/markakolyeqw2140039gold-zincirli-kolye-a59aa7.jpg","title":"baqa gold rengi zincir kolye","marka":"baqa"}},"136-":{"count":2,"keywordTitle":"200-300","imageUrl":{"src":"safir-renk-tasli-abiye-kolye-abiye-taki-oleg-cassini-11870-60-K.jpg","title":"olegcassini safir renk taşlı abiye kolye","marka":"olegcassini"}},"149-":{"count":1,"keywordTitle":"kolye","imageUrl":{"src":"productimages/sapb4l50.rnm_IMG_01_2110088715128.jpg","title":"beymen Bottega Veneta  Gold Yeşil Ataç Formlu Kadın Gümüş Kolye","marka":"beymen"}},"135-":{"count":1,"keywordTitle":"100-200","imageUrl":{"src":"/Uploads/UrunResimleri/thumb/markakolyeqw2140062gold-zincirli-klips--c86a9.jpg","title":"baqa gold zincirli büyük klipsli kolye","marka":"baqa"}},"141-":{"count":20,"keywordTitle":"700-800","imageUrl":{"src":"productimages/1krpqaac.rnp_IMG_01_2110090069134.jpg","title":"beymen Berrin Özkan  Barcelona Emerald Barok İncili Altın Kaplama Kolye","marka":"beymen"}},"139-":{"count":2,"keywordTitle":"500-600","imageUrl":{"src":"rose-gold-kristal-tasli-abiye-kolye-ve-kupe-seti-abiye-taki-oleg-cassini-18343-80-K.jpg","title":"olegcassini rose gold kristal taşlı abiye kolye ve küpe seti","marka":"olegcassini"}},"142-":{"count":23,"keywordTitle":"800-900","imageUrl":{"src":"productimages/thautorq.c0s_IMG_01_2110090069141.jpg","title":"beymen Berrin Özkan  Barcelona Emerald Barok İncili Altın Kaplama Kolye","marka":"beymen"}},"102-":{"count":1,"keywordTitle":"beymen","imageUrl":{"src":"productimages/sapb4l50.rnm_IMG_01_2110088715128.jpg","title":"beymen Bottega Veneta  Gold Yeşil Ataç Formlu Kadın Gümüş Kolye","marka":"beymen"}},"109-":{"count":17,"keywordTitle":"ipekyol","imageUrl":{"src":"660/-//ipekyol/products/FW2223/Stillife/IW6220051004265.JPG","title":"ipekyol çoklu kolye seti\n%50' ye varan","marka":"ipekyol"}},"97-":{"count":8,"keywordTitle":"koton","imageUrl":{"src":"products/2022/10/27/2605026/7b59e8f2-f4de-4cfa-a2f1-d22b14561961_size624x818.jpg","title":"koton kadın etnik detaylı metal kolye - ece sükan x koton","marka":"koton"}},"37-":{"count":4,"keywordTitle":"abiye","imageUrl":{"src":"gumus-rengi-kristal-tasli-abiye-kolye-ve-kupe-set-abiye-taki-oleg-cassini-18345-80-K.jpg","title":"olegcassini gümüş rengi kristal taşlı abiye kolye ve küpe seti","marka":"olegcassini"}},"127-":{"count":4,"keywordTitle":"olegcassini","imageUrl":{"src":"rose-gold-kristal-tasli-abiye-kolye-ve-kupe-seti-abiye-taki-oleg-cassini-18343-80-K.jpg","title":"olegcassini rose gold kristal taşlı abiye kolye ve küpe seti","marka":"olegcassini"}},"125-":{"count":7,"keywordTitle":"perspective","imageUrl":{"src":"perspective/ContentImages/Product/2022-2023-sonbahar-kis/22220246-332/kolye-0246_22220246-332_altin-altin_1_buyuk.jpg","title":"perspective bayan altin kolye 0246","marka":"perspective"}},"43-":{"count":3,"keywordTitle":"gömlek","imageUrl":{"src":"/Uploads/UrunResimleri/thumb/s-22k0250005-siyahkolyeli-salas-pamuk--9de4-2.jpg","title":"saygigiyim kolyeli salaş pamuk gömlek siyah","marka":"saygigiyim"}},"121-":{"count":9,"keywordTitle":"saygigiyim","imageUrl":{"src":"/Uploads/UrunResimleri/thumb/s-22k0250001-siyahkolyeli-firfirli-uzu-29b8-f.jpg","title":"saygigiyim kolyeli fırfırlı uzun kollu ayrobin elbise siyah","marka":"saygigiyim"}},"133-":{"count":12,"keywordTitle":"yargici","imageUrl":{"src":"mnresize/400/400/Content/Images/Originals/22165809_0.jpeg","title":"yargici ahşap detaylı zincir kolye","marka":"yargici"}},"115-":{"count":1,"keywordTitle":"zara","imageUrl":{"src":"/2022/I/0/1/p/4340/210/400/2/w/315/4340210400_15_10_1.jpg?ts=1654184330646","title":"zara KAPLUMBAĞALI KUMAŞ KOLYE Mavi","marka":"zara"}},"50-":{"count":195,"keywordTitle":"kap","imageUrl":{"src":"productimages/xc1nbf2r.jdg_IMG_01_2110087210754.jpg","title":"beymen Peracas  Urla Boncuklu Kadın Altın Kaplama Kolye","marka":"beymen"}},"145-":{"count":1,"keywordTitle":"1500","imageUrl":{"src":"productimages/sapb4l50.rnm_IMG_01_2110088715128.jpg","title":"beymen Bottega Veneta  Gold Yeşil Ataç Formlu Kadın Gümüş Kolye","marka":"beymen"}},"144-":{"count":74,"keywordTitle":"1000-1500","imageUrl":{"src":"productimages/jbomg5mg.xbz_IMG_01_2110089919020.jpg","title":"beymen Volonte  Zincir Formlu Kadın Altın Kaplama Kolye","marka":"beymen"}},"138-":{"count":29,"keywordTitle":"400-500","imageUrl":{"src":"productimages/uuni3rtl.hba_IMG_01_2110085506392.jpg","title":"beymen Berrin Özkan  Kırmızı Nazar Boncuklu Kadın Altın Kaplama Kolye","marka":"beymen"}},"143-":{"count":16,"keywordTitle":"900-1000","imageUrl":{"src":"productimages/u532jnqj.nm1_MP_0591ce7c-31ef-4ffc-b2f8-86af942f721d_1_06015818180181208565141353749_501.jpg","title":"beymen Odda75  Rose Altın Kaplama 925 Ayar Gümüş Sitare Kolye","marka":"beymen"}},"40-":{"count":1,"keywordTitle":"kazak","imageUrl":{"src":"productimages/0f5lj2ts.t1b_IMG_01_2110087715662.jpg","title":"beymen Beymen Club  Antrasit Taşlı Kolye Detaylı Kazak","marka":"beymen"}},"95-":{"count":1,"keywordTitle":"uzun","imageUrl":{"src":"productimages/lwbo3yav.dsc_MP_7f91ffba-62bd-44b4-a5bc-340cb31af048_1_79681163410255679290436738535_726.jpg","title":"beymen Cansui Design  Uzun Güneş Figürlü Altın Kaplama Kadın Bronz Kolye ","marka":"beymen"}},"140-":{"count":26,"keywordTitle":"600-700","imageUrl":{"src":"productimages/lnr5wxro.1ly_IMG_01_2110084830030.jpg","title":"beymen Berrin Özkan  Lacivert Göz Formlu Kadın Altın Kaplama Kolye","marka":"beymen"}},"94-":{"count":1,"keywordTitle":"mini","imageUrl":{"src":"productimages/s1ux5adu.lbd_IMG_01_2110090218563.jpg","title":"beymen The Attico  Pembe Zincir Kolye Detaylı Mini Kokteyl Elbise","marka":"beymen"}},"152-":{"count":1,"keywordTitle":"çanta","imageUrl":{"src":"productimages/iohaplxl.izj_IMG_01_2110088399458.jpg","title":"beymen Mers  Ucu Baget Taşlı Altın Kaplama Gümüş Kolye","marka":"beymen"}},"34-":{"count":2,"keywordTitle":"etek","imageUrl":{"src":"productimages/udcgmlft.q31_IMG_01_2110085403790.jpg","title":"beymen Bee Goddess  Bee Petek Formlu Kadın Altın Kolye","marka":"beymen"}},"137-":{"count":2,"keywordTitle":"300-400","imageUrl":{"src":"productimages/swfgb321.vqx_MP_aefa9b35-c936-4a24-a1ee-387c65dde00f_1_55511541820325514724461989177_763.jpg","title":"beymen Ecru Atelier   Valencia Altın Kaplama Kadın İnci Kolye","marka":"beymen"}},"166-":{"count":4,"keywordTitle":"bileklik","imageUrl":{"src":"productimages/5ttst0uf.g0h_MP_382a7464-8c45-4aa1-a147-9d961531b83a_1_68154205027463190231174362067_447.jpg","title":"beymen Calvin Klein  CKJ35700006 Metalik Gri Kadın Kolye ve Bileklik Seti","marka":"beymen"}},"23-":{"count":1,"keywordTitle":"bra","imageUrl":{"src":"productimages/fdk3vlxn.4ei_IMG_01_2110088876706.jpg","title":"beymen Berrin Özkan  Labradorit Boncuklu Kadın Altın Kaplama Kolye","marka":"beymen"}},"47-":{"count":2,"keywordTitle":"tişört","imageUrl":{"src":"productimages/fgihx0mo.k0n_IMG_01_2110089721999.jpg","title":"beymen Dolce&Gabbana  Siyah Bisiklet Yaka Taşlı Kolye Detaylı Sweatshirt","marka":"beymen"}},"49-":{"count":2,"keywordTitle":"sweatshirt","imageUrl":{"src":"productimages/fgihx0mo.k0n_IMG_01_2110089721999.jpg","title":"beymen Dolce&Gabbana  Siyah Bisiklet Yaka Taşlı Kolye Detaylı Sweatshirt","marka":"beymen"}},"63-":{"count":2,"keywordTitle":"bisiklet yaka","imageUrl":{"src":"productimages/fgihx0mo.k0n_IMG_01_2110089721999.jpg","title":"beymen Dolce&Gabbana  Siyah Bisiklet Yaka Taşlı Kolye Detaylı Sweatshirt","marka":"beymen"}},"154-":{"count":2,"keywordTitle":"saat","imageUrl":{"src":"productimages/k0cuwm4a.isg_MP_9ce84fa9-11f3-49f6-9074-56a57bf56dbe_1_28941047135447329326491402821_118.jpg","title":"beymen Michael Kors  MK1054SET Rose Gold Metalik Gri Kadın Kol Saati ve Kolye Seti","marka":"beymen"}},"90-":{"count":1,"keywordTitle":"kısa","imageUrl":{"src":"productimages/l5pwesqs.otq_IMG_01_2110087499463.jpg","title":"beymen Iris + Ivy  Gabrielle Kısa Çubuk Mineli Kadın Altın Kolye","marka":"beymen"}},"36-":{"count":1,"keywordTitle":"elbise","imageUrl":{"src":"productimages/s1ux5adu.lbd_IMG_01_2110090218563.jpg","title":"beymen The Attico  Pembe Zincir Kolye Detaylı Mini Kokteyl Elbise","marka":"beymen"}},"158-":{"count":1,"keywordTitle":"bot","imageUrl":{"src":"productimages/sapb4l50.rnm_IMG_01_2110088715128.jpg","title":"beymen Bottega Veneta  Gold Yeşil Ataç Formlu Kadın Gümüş Kolye","marka":"beymen"}},"15-":{"count":2,"keywordTitle":"kemer","imageUrl":{"src":"productimages/waetun3c.45n_IMG_01_2110086353841.jpg","title":"beymen Linya Jewellery  Belta Uzun Gümüş Kadın Zincir Kolye","marka":"beymen"}},"108-":{"count":16,"keywordTitle":"hm","imageUrl":{"src":"/04/b8/04b8cdbd653be4df34b1f69fe15f16c17eb415b0.jpg],origin[dam],category[],type[DESCRIPTIVESTILLLIFE],res[z],hmver[2]&call=url[file:/product/main]","title":"hm iki sıralı kolye","marka":"hm"}},"134-":{"count":39,"keywordTitle":"0-100","imageUrl":{"src":"oxxo/ContentImages/Product/22k/22KJW-KY022K034/boncuk-detayli-kolye_mix-cok-renkli_1_detay.jpg","title":"oxxo çok renkli boncuk detaylı kolye","marka":"oxxo"}},"189-":{"count":1,"keywordTitle":"deri görünümlü","imageUrl":{"src":"products/2022/12/02/2629766/132c4cf2-8c82-4589-9de6-d32bd858cb96_size624x818.jpg","title":"koton kadın choker kolye kalp detaylı deri görünümlü","marka":"koton"}},"98-":{"count":10,"keywordTitle":"lcwaikiki","imageUrl":{"src":"mnresize/600/-/pim/productimages/20211/5516060/v3/l_20211-s1md74z8-ghw_a.jpg","title":"lcwaikiki kadın kolye seti 3'lü","marka":"lcwaikiki"}},"150-":{"count":2,"keywordTitle":"küpe","imageUrl":{"src":"gumus-rengi-kristal-tasli-abiye-kolye-ve-kupe-set-abiye-taki-oleg-cassini-18345-80-K.jpg","title":"olegcassini gümüş rengi kristal taşlı abiye kolye ve küpe seti","marka":"olegcassini"}},"129-":{"count":24,"keywordTitle":"oxxo","imageUrl":{"src":"oxxo/ContentImages/Product/22k/22KJW-KY022K032/boncuk-detayli-coklu-kolye_gold-altin_1_detay.jpg","title":"oxxo altın boncuk detaylı çoklu kolye","marka":"oxxo"}},"112-":{"count":22,"keywordTitle":"roman","imageUrl":{"src":"637983414739056599-8681822276136_(4).jpg?width=500&height=750&bgcolor=white","title":"roman aksesuarlı siyah kolye","marka":"roman"}},"44-":{"count":1,"keywordTitle":"bluz","imageUrl":{"src":"/Uploads/UrunResimleri/thumb/s-22k0990001-siyahkollari-volanli-koly-da-841.jpg","title":"saygigiyim kolları volanlı kolye aksesuarlı ithal krep bluz siyah","marka":"saygigiyim"}},"91-":{"count":2,"keywordTitle":"maksi","imageUrl":{"src":"/2022/I/0/1/p/1856/325/807/2/w/315/1856325807_15_11_1.jpg?ts=1668673382551","title":"zara PARLAK TAŞLI MAKSİ KOLYE Antrasit grisi","marka":"zara"}},"164-":{"count":14,"keywordTitle":"fular","imageUrl":{"src":"/2022/I/0/1/p/7243/215/303/2/w/315/7243215303_15_11_1.jpg?ts=1668505837384","title":"zara PARLAK TAŞLI FULAR TARZI KOLYE Altın","marka":"zara"}}}