{"330-":{"count":2,"keywordTitle":"1500","imageUrl":{"src":"404/562/productimages/omfxzavc.gti_IMG_01_2110089628014.jpg","title":"beymen American Vintage  Sarı Gömlek Yaka Palto","marka":"beymen"}},"274-":{"count":2,"keywordTitle":"palto","imageUrl":{"src":"404/562/productimages/13xoau1v.dlm_IMG_01_2110089488236.jpg","title":"beymen Vince  Kahverengi Gömlek Yaka Palto","marka":"beymen"}},"296-":{"count":2,"keywordTitle":"gömlek","imageUrl":{"src":"404/562/productimages/13xoau1v.dlm_IMG_01_2110089488236.jpg","title":"beymen Vince  Kahverengi Gömlek Yaka Palto","marka":"beymen"}},"187-":{"count":1,"keywordTitle":"kahverengi","imageUrl":{"src":"404/562/productimages/13xoau1v.dlm_IMG_01_2110089488236.jpg","title":"beymen Vince  Kahverengi Gömlek Yaka Palto","marka":"beymen"}},"221-":{"count":2,"keywordTitle":"beymen","imageUrl":{"src":"404/562/productimages/omfxzavc.gti_IMG_01_2110089628014.jpg","title":"beymen American Vintage  Sarı Gömlek Yaka Palto","marka":"beymen"}}}